pysignalfd.py
pysignalfd-0.0.1.dist-info/LICENSE
pysignalfd-0.0.1.dist-info/METADATA
pysignalfd-0.0.1.dist-info/WHEEL
pysignalfd-0.0.1.dist-info/top_level.txt
pysignalfd-0.0.1.dist-info/RECORD
