Metadata-Version: 2.1
Name: pysignalfd
Version: 0.0.1
Summary: A pure Python wrapper of signalfd(2)
Home-page: https://github.com/jschwinger23/pysignalfd
Author: lzc
Author-email: greyschwinger@gmail.com
License: BSD
Platform: UNKNOWN
Classifier: Development Status :: 5 - Production/Stable
Classifier: Intended Audience :: Developers
Classifier: License :: OSI Approved :: BSD License
Classifier: Operating System :: POSIX :: Linux
Classifier: Programming Language :: Python :: 3.5
Classifier: Programming Language :: Python :: Implementation :: CPython
Classifier: Topic :: Utilities
Requires-Python: >=3.5
